erich/__init__.py
erich/erich.py
erich-0.0.2.dist-info/LICENSE
erich-0.0.2.dist-info/METADATA
erich-0.0.2.dist-info/WHEEL
erich-0.0.2.dist-info/top_level.txt
erich-0.0.2.dist-info/zip-safe
erich-0.0.2.dist-info/RECORD
