Metadata-Version: 2.1
Name: erich
Version: 0.0.2
Summary: Decorators for better error handling
Author: Robin Bergewski
License: unlicense
Project-URL: Homepage, https://github.com/Sojamann/erich
Keywords: decorator,decorators,error,errors
Classifier: Programming Language :: Python :: 3
Classifier: License :: OSI Approved :: MIT License
Classifier: Operating System :: OS Independent
Requires-Python: >=3.7
License-File: LICENSE
